{
  "schemaVersion": 1,
  "status": "ok",
  "source": "flagcounter-history",
  "host": "zwt233.github.io",
  "timezone": "Asia/Shanghai",
  "generatedAt": "2026-07-01T06:14:46.331Z",
  "updatedLabel": "07-01 14:14",
  "detailsUrl": "https://flagcounter.com/more30/z9BD",
  "periods": {
    "today": {
      "label": "Today",
      "pageviews": 34,
      "visits": 19,
      "date": "2026-07-01"
    },
    "month": {
      "label": "This month",
      "pageviews": 34,
      "visits": 19,
      "days": 1
    },
    "total": {
      "label": "Total",
      "pageviews": 3006,
      "visits": 2125
    }
  },
  "message": "Pageviews are generated from FlagCounter History using the Flag Counter Views column."
}
