{
  "schemaVersion": 1,
  "status": "ok",
  "source": "flagcounter-history",
  "host": "zwt233.github.io",
  "timezone": "Asia/Shanghai",
  "generatedAt": "2026-07-03T23:28:35.923Z",
  "updatedLabel": "07-04 07:28",
  "detailsUrl": "https://flagcounter.com/more30/z9BD",
  "periods": {
    "today": {
      "label": "Today",
      "pageviews": 91,
      "visits": 73,
      "date": "2026-07-04"
    },
    "month": {
      "label": "This month",
      "pageviews": 260,
      "visits": 200,
      "days": 3
    },
    "total": {
      "label": "Total",
      "pageviews": 3232,
      "visits": 2306
    }
  },
  "message": "Pageviews are generated from FlagCounter History using the Flag Counter Views column."
}
