{
  "schemaVersion": 1,
  "status": "ok",
  "source": "flagcounter-history",
  "host": "zwt233.github.io",
  "timezone": "Asia/Shanghai",
  "generatedAt": "2026-06-20T11:30:33.594Z",
  "updatedLabel": "06-20 19:30",
  "detailsUrl": "https://flagcounter.com/more30/z9BD",
  "periods": {
    "today": {
      "label": "Today",
      "pageviews": 52,
      "visits": 27,
      "date": "2026-06-20"
    },
    "month": {
      "label": "This month",
      "pageviews": 1850,
      "visits": 1358,
      "days": 17
    },
    "total": {
      "label": "Total",
      "pageviews": 1930,
      "visits": 1367
    }
  },
  "message": "Pageviews are generated from FlagCounter History using the Flag Counter Views column."
}
