{
  "schemaVersion": 1,
  "status": "ok",
  "source": "flagcounter-history",
  "host": "zwt233.github.io",
  "timezone": "Asia/Shanghai",
  "generatedAt": "2026-07-17T14:18:18.564Z",
  "updatedLabel": "07-17 22:18",
  "detailsUrl": "https://flagcounter.com/more30/z9BD",
  "periods": {
    "today": {
      "label": "Today",
      "pageviews": 67,
      "visits": 46,
      "date": "2026-07-17"
    },
    "month": {
      "label": "This month",
      "pageviews": 1424,
      "visits": 1043,
      "days": 16
    },
    "total": {
      "label": "Total",
      "pageviews": 4396,
      "visits": 3149
    }
  },
  "message": "Pageviews are generated from FlagCounter History using the Flag Counter Views column."
}
