{
  "schemaVersion": 1,
  "status": "ok",
  "source": "flagcounter-history",
  "host": "zwt233.github.io",
  "timezone": "Asia/Shanghai",
  "generatedAt": "2026-06-28T23:17:36.994Z",
  "updatedLabel": "06-29 07:17",
  "detailsUrl": "https://flagcounter.com/more30/z9BD",
  "periods": {
    "today": {
      "label": "Today",
      "pageviews": 79,
      "visits": 56,
      "date": "2026-06-29"
    },
    "month": {
      "label": "This month",
      "pageviews": 2651,
      "visits": 1928,
      "days": 25
    },
    "total": {
      "label": "Total",
      "pageviews": 2731,
      "visits": 1937
    }
  },
  "message": "Pageviews are generated from FlagCounter History using the Flag Counter Views column."
}
